phase/__init__.py
phase/phase.py
phase/utils/__init__.py
phase/utils/const.py
phase/utils/crypto.py
phase/utils/exceptions.py
phase/utils/misc.py
phase/utils/network.py
phase/utils/phase_io.py
phase/utils/secret_referencing.py
phase_dev-2.1.2.dist-info/licenses/LICENSE
phase_dev-2.1.2.dist-info/METADATA
phase_dev-2.1.2.dist-info/WHEEL
phase_dev-2.1.2.dist-info/top_level.txt
phase_dev-2.1.2.dist-info/RECORD
