Metadata-Version: 2.4
Name: phase_dev
Version: 2.1.2
Summary: Python SDK for Phase secrets manager
Author-email: Phase <rohan@phase.dev>
Project-URL: Homepage, https://phase.dev
Project-URL: Documentation, https://docs.phase.dev
Classifier: Programming Language :: Python :: 3
Classifier: License :: OSI Approved :: MIT License
Classifier: Operating System :: OS Independent
Requires-Python: >=3.10
License-File: LICENSE
Requires-Dist: pyNaCl>=1.5.0
Requires-Dist: requests>=2.32.0
Provides-Extra: dev
Requires-Dist: pip-tools; extra == "dev"
Requires-Dist: pytest; extra == "dev"
Dynamic: license-file
